[
  {
    "type": "java",
    "name": "jar (in project Frc-Eagles-2025)",
    "extensions": [
      {
        "name": "Sim GUI",
        "libName": "C:\\Users\\kerol\\Pictures\\Frc-Eagles-2025\\build\\jni\\release\\halsim_gui.dll",
        "defaultEnabled": true
      },
      {
        "name": "Use Real DriverStation",
        "libName": "C:\\Users\\kerol\\Pictures\\Frc-Eagles-2025\\build\\jni\\release\\halsim_ds_socket.dll",
        "defaultEnabled": false
      }
    ],
    "environment": {},
    "libraryDir": "C:\\Users\\kerol\\Pictures\\Frc-Eagles-2025\\build\\jni\\release",
    "mainClassName": "frc.robot.Main"
  }
]